{
	"label": "GM Toolkit",
	"entries": [
		{
			"id": "Dark Whispers",
			"name": "Susurros Oscuros",
			"description": "Susurros Oscuros gen\u00E9ricos para usar como ejemplos de referencia para la macro Send Dark Whispers.",
			"results": {
				"1-1": "Deja marchar a tu presa.",
				"2-2": "Golpea 'accidentalmente' a un aliado.",
				"3-3": "Qu\u00E9date dormido durante la guardia.",
				"4-4": "Arrod\u00EDllate ante el Magister. Mu\u00E9strale tu lealtad.",
				"5-5": "Nadie es tan bueno ni tiene tanta suerte. Sin importar lo poderoso o popular que sea. \u00A1Ll\u00E1male tramposo!",
				"6-6": "No est\u00E1s tan preparado como pensabas.",
				"7-7": "Ejerce tu autoridad. Usa de ejemplo a los m\u00E1s d\u00E9biles o vulnerables.",
				"8-8": "Ese gran indestructible de ah\u00ED te est\u00E1 mirando raro. No lo aguantes. Defiende tu honor. P\u00FAblicamente y solo.",
				"9-9": "No has recorrido todo este camino para hacer amigos. A veces acabas haciendo enemigos. \u00C9sta es una de esas oportunidades.",
				"10-10": "Los secretos son una carga. S\u00E9 generoso y comp\u00E1rtelos."
				}
		}
	]
}